MirahezeBots/__init__.py
MirahezeBots/dbclean.py
MirahezeBots/version.py
MirahezeBots/plugins/__init__.py
MirahezeBots/plugins/goofy.py
MirahezeBots/plugins/miraheze.py
MirahezeBots/plugins/phab.py
MirahezeBots/plugins/responses.py
MirahezeBots/plugins/rss.py
MirahezeBots/plugins/shortlinks.py
MirahezeBots/plugins/status.py
MirahezeBots/plugins/welcome.py
MirahezeBots/tests/__init__.py
MirahezeBots/tests/models.py
MirahezeBots/tests/test_general.py
MirahezeBots/utils/__init__.py
MirahezeBots/utils/mwapihandler.py
MirahezeBot_Plugins-9.1.5.dist-info/LICENSE
MirahezeBot_Plugins-9.1.5.dist-info/METADATA
MirahezeBot_Plugins-9.1.5.dist-info/WHEEL
MirahezeBot_Plugins-9.1.5.dist-info/entry_points.txt
MirahezeBot_Plugins-9.1.5.dist-info/top_level.txt
MirahezeBot_Plugins-9.1.5.dist-info/RECORD
