Metadata-Version: 2.1
Name: MirahezeBot-Plugins
Version: 9.1.5
Summary: Sopel Plugins for Miraheze Bots
Home-page: https://github.com/MirahezeBots/MirahezeBots
Author: MirahezeBot Contributors
Author-email: bots@miraheze.org
License: Eiffel Forum License, version 2
Platform: UNKNOWN
Classifier: Development Status :: 5 - Production/Stable
Classifier: Intended Audience :: Developers
Classifier: Intended Audience :: System Administrators
Classifier: License :: Eiffel Forum License (EFL)
Classifier: License :: OSI Approved :: Eiffel Forum License
Classifier: Operating System :: POSIX :: Linux
Classifier: Operating System :: Microsoft :: Windows
Classifier: Operating System :: MacOS
Classifier: Programming Language :: Python :: 3.6
Classifier: Programming Language :: Python :: 3.7
Classifier: Programming Language :: Python :: 3.8
Classifier: Programming Language :: Python :: 3.9
Classifier: Topic :: Communications :: Chat :: Internet Relay Chat
Requires-Python: >=3.7
License-File: LICENSE
Requires-Dist: feedparser (<7.0.0,>=6.0.2)
Requires-Dist: requests (<2.27.0,>=2.26.0)
Requires-Dist: idna (<4,>=3.2)
Requires-Dist: sopel (<8,>=7.1.2)
Requires-Dist: SQLAlchemy (<1.4.0,>=1.3.20)
Requires-Dist: MirahezeBots-jsonparser (<2.0.0,>=1.0.4)
Requires-Dist: sopel-plugins.adminlist (>=1.0.7)
Requires-Dist: sopel-plugins.channelmgnt (>=2.1.1)
Requires-Dist: sopel-plugins.joinall (>=1.0.4)
Requires-Dist: urllib3 (>=1.26.6)
